automation_frame/__init__.py
automation_frame/tools/__init__.py
automation_frame/tools/tool_http.py
automation_frame-1.1.dist-info/LICENSE
automation_frame-1.1.dist-info/METADATA
automation_frame-1.1.dist-info/WHEEL
automation_frame-1.1.dist-info/top_level.txt
automation_frame-1.1.dist-info/RECORD
