Metadata-Version: 2.1
Name: automation-frame
Version: 1.1
Summary: 一个非常NB的包
Author: zhangsan
Author-email: zhangsan@live.com
Classifier: Programming Language :: Python :: 3
Classifier: License :: OSI Approved :: MIT License
Classifier: Operating System :: OS Independent
Requires-Python: >=3
License-File: LICENSE
Requires-Dist: pillow
